seabird/__init__.py
seabird/checks.py
seabird/cli.py
seabird/cnv.py
seabird/exceptions.py
seabird/netcdf.py
seabird/qc.py
seabird/utils.py
seabird/version.py
seabird/rules/cnv.json
seabird/rules/cnv.yaml
seabird/rules/cnv2.json
seabird/rules/cnv3.json
seabird/rules/cnv4.json
seabird/rules/cnv_binary.json
seabird/rules/cnv_btl.json
seabird/rules/refnames.json
seabird-0.12.0.dist-info/AUTHORS.rst
seabird-0.12.0.dist-info/LICENSE.rst
seabird-0.12.0.dist-info/METADATA
seabird-0.12.0.dist-info/WHEEL
seabird-0.12.0.dist-info/entry_points.txt
seabird-0.12.0.dist-info/top_level.txt
seabird-0.12.0.dist-info/RECORD
