Metadata-Version: 2.1
Name: seabird
Version: 0.12.0
Summary: Parser for Sea-Bird's CTD and TSG
Author: Guilherme Castelao , Luiz Irber
Author-email: guilherme@castelao.net, luiz.irber@gmail.com
License: 3-clause BSD
Project-URL: repository, https://github.com/castelao/seabird
Keywords: oceanography,ocean data,CTD,TSG,SeaBird,hydrography,parser
Platform: any
Classifier: Development Status :: 5 - Production/Stable
Classifier: Natural Language :: English
Classifier: Intended Audience :: Science/Research
Classifier: License :: OSI Approved :: BSD License
Classifier: Operating System :: OS Independent
Classifier: Programming Language :: Python :: 3
Classifier: Programming Language :: Python :: 3.6
Classifier: Programming Language :: Python :: 3.7
Classifier: Programming Language :: Python :: 3.8
Classifier: Programming Language :: Python :: 3.9
Classifier: Programming Language :: Python :: 3.10
Classifier: Topic :: Scientific/Engineering
Requires-Python: >=3.6
License-File: LICENSE.rst
License-File: AUTHORS.rst
Requires-Dist: numpy (>=1.14)
Requires-Dist: Click (>=6.6)
Provides-Extra: cdf
Requires-Dist: netCDF4 (>=1.4) ; extra == 'cdf'
Provides-Extra: qc
Requires-Dist: cotede (>=0.20.2) ; extra == 'qc'
Provides-Extra: test
Requires-Dist: hypothesis (>=6.29.3) ; extra == 'test'
Requires-Dist: pytest (>=5.0.0) ; extra == 'test'
Requires-Dist: pytest-cov[all] ; extra == 'test'
Requires-Dist: pip (>=9.0.1) ; extra == 'test'
Requires-Dist: flake8 (>=3.2.1) ; extra == 'test'
Requires-Dist: tox (>=2.3.3) ; extra == 'test'
Requires-Dist: coverage (>=4.2) ; extra == 'test'
Requires-Dist: pytest (>=3.0.5) ; extra == 'test'
Requires-Dist: supportdata (>=0.1.2) ; extra == 'test'
Requires-Dist: twine (>=1.8.1) ; extra == 'test'
